<?xml version="1.0"?>
<!-- EPS (ColoradoFourWheeler) Plugin -->
<Actions>
	<!-- Defaults to the main ColoradoFourWheeler forum on Indigo -->
	<SupportURL>http://forums.indigodomo.com/viewforum.php?f=192</SupportURL>
	
	<!-- All plugins that monitor other devices will have an update action -->
	<Action id="update" deviceFilter="self" uiPath="DeviceActions">
		<Name>Update</Name>
		<CallbackMethod>updateDevice</CallbackMethod>
	</Action>
	
	<Action id="forceOn" deviceFilter="self" uiPath="DeviceActions">
		<Name>Force to an On state</Name>
		<CallbackMethod>forceState</CallbackMethod>
	</Action>
	
	<Action id="forceOff" deviceFilter="self" uiPath="DeviceActions">
		<Name>Force to an Off state</Name>
		<CallbackMethod>forceState</CallbackMethod>
	</Action>
	
</Actions>
